tamil_translite/__init__.py
tamil_translite/olipeyarppu.py
tamil_translite/translit_rules.json
tamil_translite/translite.py
tests/__init__.py
tests/test_translite.py
tamil_translite-0.2.6.dist-info/LICENSE
tamil_translite-0.2.6.dist-info/METADATA
tamil_translite-0.2.6.dist-info/WHEEL
tamil_translite-0.2.6.dist-info/top_level.txt
tamil_translite-0.2.6.dist-info/RECORD
