Metadata-Version: 2.1
Name: tamil-translite
Version: 0.2.6
Summary: A package for phonetic transliteration of Tamil text into English.
Home-page: https://github.com/irahnarak/tamil_translite
Author: Harikaran Saravanan
Author-email: irahnarak@gmail.com
License: UNKNOWN
Keywords: Tamil,Transliteration,Phonetic,Tamil to English
Platform: UNKNOWN
Classifier: Programming Language :: Python :: 3
Classifier: License :: OSI Approved :: MIT License
Classifier: Operating System :: OS Independent
Requires-Python: >=3.9
License-File: LICENSE
